Metadata-Version: 2.4
Name: x_4357_make_copilot_cli_one_time_setup_x
Version: 0.20.17
Summary: Non-interactive Copilot CLI probe that discovers Copilot Requests PATs and verifies github-copilot-cli readiness.
Author-email: "RRGM (Software Tech Lead, Primus Pilus Night Watch AI Corp.)" <foo@bar.com>
Requires-Python: >=3.8
